odoo/addons/brand/README.rst
odoo/addons/brand/__init__.py
odoo/addons/brand/__manifest__.py
odoo/addons/brand/i18n/brand.pot
odoo/addons/brand/i18n/de.po
odoo/addons/brand/i18n/es.po
odoo/addons/brand/i18n/es_AR.po
odoo/addons/brand/i18n/fr.po
odoo/addons/brand/i18n/fr_FR.po
odoo/addons/brand/i18n/hr.po
odoo/addons/brand/i18n/it.po
odoo/addons/brand/i18n/nl.po
odoo/addons/brand/i18n/pl.po
odoo/addons/brand/i18n/pt.po
odoo/addons/brand/models/__init__.py
odoo/addons/brand/models/res_brand.py
odoo/addons/brand/models/res_brand_mixin.py
odoo/addons/brand/models/res_company.py
odoo/addons/brand/models/res_config_settings.py
odoo/addons/brand/readme/CONTRIBUTORS.md
odoo/addons/brand/readme/CREDITS.md
odoo/addons/brand/readme/DESCRIPTION.md
odoo/addons/brand/readme/USAGE.md
odoo/addons/brand/security/res_brand.xml
odoo/addons/brand/static/description/icon.png
odoo/addons/brand/static/description/index.html
odoo/addons/brand/tests/__init__.py
odoo/addons/brand/tests/common.py
odoo/addons/brand/tests/test_brand.py
odoo/addons/brand/tests/test_brand_mixin.py
odoo/addons/brand/views/res_brand.xml
odoo/addons/brand/views/res_config_settings.xml
odoo_addon_brand-19.0.1.0.0.2.dist-info/METADATA
odoo_addon_brand-19.0.1.0.0.2.dist-info/WHEEL
odoo_addon_brand-19.0.1.0.0.2.dist-info/top_level.txt
odoo_addon_brand-19.0.1.0.0.2.dist-info/RECORD
