Metadata-Version: 2.1
Name: odoo-addon-brand
Version: 19.0.1.0.0.2
Requires-Dist: odoo==19.0.*
Summary: This is a base addon for brand modules. It adds the brand object and its menu and define an abstract model to be inherited from branded objects
Home-page: https://github.com/OCA/brand
License: LGPL-3
Author: Odoo Community Association (OCA), ACSONE SA/NV
Author-email: support@odoo-community.org
Classifier: Programming Language :: Python
Classifier: Framework :: Odoo
Classifier: Framework :: Odoo :: 19.0
Classifier: License :: OSI Approved :: GNU Lesser General Public License v3 (LGPLv3)
